lando_cli/cli.py
lando_cli-0.3.0.dist-info/licenses/LICENSE
lando_cli-0.3.0.dist-info/METADATA
lando_cli-0.3.0.dist-info/WHEEL
lando_cli-0.3.0.dist-info/entry_points.txt
lando_cli-0.3.0.dist-info/top_level.txt
lando_cli-0.3.0.dist-info/RECORD
